{
  "title": "Mom’s Chicken Cutlets",
  "slug": "moms-chicken-cutlets",
  "date": "20150526",
  "publishedDate": "2015-05-26",
  "excerpt": "<p><p>Recipe: Mom’s Chicken Cutlets One of the earliest things I remember helping my mom cook was her chicken cutlets. She’d lay out three bowls (one for flour, one for eggs, and one for breadcrumbs) and let me dip the chicken in to each, carefully coating it on each side. It made my fingers disgusting, but I […]</p></p>",
  "content": "<p>Recipe: Mom’s Chicken Cutlets</p><p>One of the earliest things I remember helping my mom cook was her chicken cutlets. She’d lay out three bowls (one for flour, one for eggs, and one for breadcrumbs) and let me dip the chicken in to each, carefully coating it on each side. It made my fingers disgusting, but I loved every minute of it. Especially because I knew it meant very soon I’d get to eat my mother’s amazing chicken cutlets.</p><p>Many years later, the recipe is still the same, with a very slight tweak from my father (whose birthday is today!!) My Husband (who also celebrates a birthday this month) had a hankering for chicken cutlets, mashed potatoes and honey glazed carrots, so I thought I’d share a few of the recipes with you. Today will be “Mom’s Chicken Cutlets” day, and later in the week will be “Dad’s Honey Glazed Carrots” day! I’ve always preferred these chicken cutlets to anything in a store or restaurant because they just taste SO MUCH BETTER! Hope you try out the recipe and fall in love too!</p><p>That’s not greasy oil, that’s delicious honey! Mmm!</p><p>The amount for each ingredient will depend on how much you are cooking, so I didn’t include specific amounts below. If you are cooking 4-6 cutlets (a typical package of chicken breasts), you will need about 3/4 cup of flour, 1 to 1 1/2 cups of breadcrumbs and two eggs. I always start with the minimum and add extra as I go if needed, so I’m not wasteful!</p><h2>Ingredients:</h2><ul><li><p>Boneless, trimmed, thin cut chicken breasts</p></li><li><p>Italian seasoned breadcrumbs</p></li><li><p>Flour (all-purpose white or wheat)</p></li><li><p>Eggs (2+… see above)</p></li><li><p>Olive oil (enough to generously cover the entire bottom of your frying pan)</p></li><li><p>Honey</p></li><li><p>Salt, pepper, onion powder, garlic powder, paprika</p></li></ul><h2>Instructions:</h2><ul><li><p>If your chicken breasts aren’t trimmed of fat, etc. yet, do so before you get started!</p></li><li><p>Pound cutlets with a tenderizer. If they are VERY thin cut, only do this a little. You aren’t looking for a chicken pancake!</p></li><li><p>Season each side of each breast with salt, pepper, onion powder, garlic powder and paprika (just a sprinkle of each, to taste).</p></li><li><p>Line up three bowls, and place the flour, eggs (remember to scramble them!), and breadcrumbs in them, respectively.</p><em><p>Tip: Remember “F-E-B-ruary”: F(lour)-E(ggs)-B(readcrumbs)</p></em></li><li><p>Add olive oil to your pan, enough to cover the entire bottom of the pan and then some. Maybe about half an inch of oil deep. Turn on low heat and let it start warming up.</p></li><li><p>With CLEAN HANDS (take your wedding rings off, first!), and a fork or tongs, completely coat each side of the chicken breast in the flour, then eggs, then breadcrumbs. Be sure to gently shake off excess flour/breadcrumbs when on those steps.</p></li><li><p>Set chicken aside on a plate. Repeat for each breast.</p></li><li><p>Turn pan to medium-high (being careful!) to let it finish heating up while you clean up the mess you just made with the flour.</p></li><li><p>Test hotness of pan by flicking a drop or two of water in to it. If it sizzles, it’s ready for the chicken.</p></li><li><p>Place the chicken breasts in the pan and let cook approximately four minutes on one side (or until you see at least halfway up the side of the breast is browned).</p></li><li><p>Flip over to cook other side of breast until the whole cutlet is almost as golden brown as you like.</p></li><li><p>Add a squirt of honey to the top of the breast and let cook the last minute with the honey on top. You will only be adding honey to this one side, because the honey and oil do not get along. Trust me.</p></li><li><p>Transfer to a clean plate that is covered in paper towels, to soak up the oil. Make sure you place the breast honey-side-up, so it doesn’t stick to the paper!</p></li><li><p>Repeat for all breasts, cooking a few at a time. Feel free to use your tongs to occasionally lift up the chicken and check for doneness on other side. Add oil to the pan if necessary, but remember to let it catch back up to the correct heat before adding more chicken.</p><em><p>If you ever end up with soggy chicken cutlets, it is because your oil was not hot enough!</p></em></li><li><p>Let chicken cool on the paper towels until ready to eat. It’s delicious hot with mashed potatoes and carrots, cold the next day on a sandwich, or with cheese for chicken parm! YUM!</p></li></ul><p>Don’t these carrots look wonderful? Recipe coming soon!</p><p>If you try this recipe, let me know how it goes in the comments! What is your favorite side dish for chicken cutlets?</p>",
  "featuredImage": {
    "src": "/posts/moms-chicken-cutlets/featured.png",
    "width": 1024,
    "height": 1024,
    "alt": "Mom's Chicken Cutlets, recipe by Katie Crafts; http://www.katiecrafts.com"
  },
  "categories": [
    {
      "id": 7,
      "name": "Cooks",
      "slug": "cooks"
    }
  ],
  "tags": [
    {
      "id": 338,
      "name": "chicken",
      "slug": "chicken"
    },
    {
      "id": 1351,
      "name": "chicken cutlets",
      "slug": "chicken-cutlets"
    },
    {
      "id": 21,
      "name": "cooks",
      "slug": "cooks-2"
    },
    {
      "id": 309,
      "name": "food",
      "slug": "food"
    },
    {
      "id": 557,
      "name": "mom",
      "slug": "mom"
    },
    {
      "id": 23,
      "name": "recipe",
      "slug": "recipe"
    }
  ]
}
