{
  "title": "Sunday, Lazy Sunday!",
  "slug": "sunday-lazy-sunday",
  "date": "20140720",
  "publishedDate": "2014-07-20",
  "excerpt": "<p><p>Our normal “Sunday Funday” will be a “MONDAY Funday” tomorrow instead, as Katie Crafts has been having technically difficulties all day and the post couldn’t get finished… and now it’s super late and I’m too tired! Haha! Enjoy these pics of our kitties and the kitties we are sitting for right now instead! Happy Sunday! […]</p></p>",
  "content": "<p>Our normal “Sunday Funday” will be a “MONDAY Funday” tomorrow instead, as Katie Crafts has been having technically difficulties all day and the post couldn’t get finished… and now it’s super late and I’m too tired! Haha! Enjoy these pics of our kitties and the kitties we are sitting for right now instead! Happy Sunday!</p><p><img class=\"size-medium post__image\" src=\"/posts/sunday-lazy-sunday/img-4562.jpg\" alt=\"Sunday, Lazy Sunday on Katie Crafts; http://www.katiecrafts.com\" width=\"663\" height=\"457\"><img class=\"size-medium post__image\" src=\"/posts/sunday-lazy-sunday/img-4265.jpg\" alt=\"Sunday, Lazy Sunday on Katie Crafts; http://www.katiecrafts.com\" width=\"663\" height=\"1173\"></p><p><img class=\"size-medium post__image\" src=\"/posts/sunday-lazy-sunday/img-4190.jpg\" alt=\"Sunday, Lazy Sunday on Katie Crafts; http://www.katiecrafts.com\" width=\"663\" height=\"994\"></p>",
  "featuredImage": {
    "src": "/posts/sunday-lazy-sunday/featured.jpg",
    "width": 1280,
    "height": 1396,
    "alt": "Sunday, Lazy Sunday on Katie Crafts; http://www.katiecrafts.com"
  },
  "categories": [
    {
      "id": 9,
      "name": "Cats",
      "slug": "cats"
    }
  ],
  "tags": [
    {
      "id": 370,
      "name": "kitty",
      "slug": "kitty"
    },
    {
      "id": 37,
      "name": "loves cats",
      "slug": "loves-cats-2"
    },
    {
      "id": 46,
      "name": "lucky",
      "slug": "lucky"
    },
    {
      "id": 19,
      "name": "mabel",
      "slug": "mabel"
    },
    {
      "id": 790,
      "name": "marshal",
      "slug": "marshal"
    },
    {
      "id": 791,
      "name": "samantha",
      "slug": "samantha"
    }
  ]
}
