{
  "title": "",
  "slug": "sunday-well-spent",
  "date": "20150823",
  "publishedDate": "2015-08-23",
  "excerpt": "<p><p>A Sunday well spent brings a week of content.</p></p>",
  "content": "<p><img class=\"size-full post__image\" src=\"/posts/sunday-well-spent/sunday-well-spent.png\" alt=\"A Sunday well spent brings a week of content. http://www.katiecrafts.com\" width=\"980\" height=\"980\"></p><p><em>A Sunday well spent brings a week of content.</em></p>",
  "categories": [
    {
      "id": 1,
      "name": "Hodgepodge",
      "slug": "hodgepodge"
    }
  ],
  "tags": [
    {
      "id": 1343,
      "name": "qotd",
      "slug": "qotd"
    },
    {
      "id": 97,
      "name": "quotes",
      "slug": "quotes"
    },
    {
      "id": 1452,
      "name": "sunday",
      "slug": "sunday"
    }
  ]
}
