{
  "title": "",
  "slug": "mabel-the-helper",
  "date": "20141025",
  "publishedDate": "2014-10-25",
  "excerpt": "<p><p>Mabel is a great help when it comes to stuffing the animals I’m sewing. She makes sure no one touches the filling but me. And her.</p></p>",
  "content": "<p><img class=\"size-medium post__image\" src=\"/posts/mabel-the-helper/img-5973.jpg\" alt=\"Mabel The Helper on Katie Crafts; http://www.katiecrafts.com\" width=\"663\" height=\"497\"></p><p>Mabel is a great help when it comes to stuffing the animals I’m sewing. She makes sure no one touches the filling but me. And her.</p>",
  "categories": [
    {
      "id": 9,
      "name": "Cats",
      "slug": "cats"
    }
  ],
  "tags": [
    {
      "id": 1008,
      "name": "crafting",
      "slug": "crafting"
    },
    {
      "id": 370,
      "name": "kitty",
      "slug": "kitty"
    },
    {
      "id": 37,
      "name": "loves cats",
      "slug": "loves-cats-2"
    },
    {
      "id": 19,
      "name": "mabel",
      "slug": "mabel"
    }
  ]
}
